{
  "tags": [
    {
      "name": "release",
      "version": "1.25.0",
      "commit": "d7f965e",
      "upstream": "Releases",
      "lastUpdated": "2021-08-27T19:55:51.762Z"
    },
    {
      "name": "testing",
      "version": "",
      "commit": "",
      "upstream": "",
      "lastUpdated": ""
    },
    {
      "name": "nightly",
      "version": "4f654b98c31c33cafc50785d0c0a7fb4a7dbe859",
      "commit": "2d312fc",
      "upstream": "Every commit to develop",
      "lastUpdated": "2021-08-27T20:16:45.900Z"
    }
  ],
  "pulls": 1827116,
  "stars": 8
}
